[
    {
        "from": "github-action",
        "to": "byuJR",
        "amount": 5.974746,
        "timestamp": "2025-02-13T03:37:40Z",
        "txid": "994c7a0712b91819eed51f121b9b76a2fd77551c6f25d4c4869c21a4c3544ceb"
    },
    {
        "from": "byuJR",
        "to": "figuran04",
        "amount": 2.23,
        "timestamp": "2025-02-13T03:40:26Z",
        "txid": "49490ee2935b10cadd58e2a59a1518acf99a54e3762f38f63f06d8c4fd3f61a6"
    },
    {
        "from": "github-action",
        "to": "Lawyeritchi",
        "amount": 0.039254,
        "timestamp": "2025-02-13T03:53:41Z",
        "txid": "c47369ec70c71f4bfa6a3d876c33a88a67e9e1536802a5d1b91cc4b477aacaf9"
    },
    {
        "from": "figuran04",
        "to": "Lawyeritchi",
        "amount": 3.0,
        "timestamp": "2025-02-13T04:00:08Z",
        "txid": "c1fa7a20dbee25cb0ebfe0148b215c3818fe82078fbbf59242cf555c63e2f0c0"
    }
]